openg2p_g2p_bridge_models/__init__.py
openg2p_g2p_bridge_models/errors/__init__.py
openg2p_g2p_bridge_models/errors/codes.py
openg2p_g2p_bridge_models/errors/exceptions.py
openg2p_g2p_bridge_models/models/__init__.py
openg2p_g2p_bridge_models/models/account_statement.py
openg2p_g2p_bridge_models/models/benefit_program_configuration.py
openg2p_g2p_bridge_models/models/common_enums.py
openg2p_g2p_bridge_models/models/disbursement.py
openg2p_g2p_bridge_models/models/disbursement_envelope.py
openg2p_g2p_bridge_models/schemas/__init__.py
openg2p_g2p_bridge_models/schemas/account_statement.py
openg2p_g2p_bridge_models/schemas/benefit_program_configuration.py
openg2p_g2p_bridge_models/schemas/disbursement.py
openg2p_g2p_bridge_models/schemas/disbursement_envelope.py
openg2p_g2p_bridge_models/schemas/disbursement_status.py
openg2p_g2p_bridge_models-1.1.0.dist-info/METADATA
openg2p_g2p_bridge_models-1.1.0.dist-info/WHEEL
openg2p_g2p_bridge_models-1.1.0.dist-info/RECORD
